Workbook
Name Slicer_Category: #N/A
Name Slicer_Discount_Applied: #N/A
Name Slicer_Location: #N/A
Name Slicer_Payment_Method: #N/A

Sheet Sheet4
A3: Row Labels | B3: Sum of Price Per Unit
A4: Credit Card | B4: 57920 | D4: Row Labels | E4: Sum of Total Spent
A5: Digital Wallet | B5: 58378.5 | D5: Cash | E5: 0.3477673
A6: Cash | B6: 61269 | D6: Credit Card | E6: 0.32778072
A7: Grand Total | B7: 177567.5 | D7: Digital Wallet | E7: 0.32445198
D8: Grand Total | E8: 1
A12: Row Labels | B12: Sum of Total Spent
A13: 2022 | B13: 329939 | D13: Row Labels | E13: Count of Transaction ID
A14: 2023 | B14: 303318 | D14: Milk Products | E14: 0.12917271
A15: 2024 | B15: 338900 | D15: Computers and electric accessories | E15: 0.12838105 | G15: Top category | H15: Milk product: 12.93%
A16: 2025 | B16: 16356 | D16: Butchers | E16: 0.12626996
A17: Grand Total | B17: 988513 | D17: Food | E17: 0.12561024
D18: Electric household essentials | E18: 0.12521441
D19: Furniture | E19: 0.12376303
D20: Beverages | E20: 0.12138805
D21: Patisserie | E21: 0.12020055
D22: Grand Total | E22: 1

Sheet dashboard

Sheet Sheet5
A3: Row Labels | B3: Sum of Quantity
A4: In-store | B4: 20635
A5: Online | B5: 21484
A6: Grand Total | B6: 42119

Sheet Sheet6
A3: Row Labels | B3: Sum of Price Per Unit
A4: 3 | B4: 17987.5
A5: 5 | B5: 18238
A6: 8 | B6: 18267.5
A7: 6 | B7: 18595
A8: 10 | B8: 18645.5
A9: Grand Total | B9: 91733.5

Sheet retail_store_sales (1)
A1: Transaction ID | B1: Customer ID | C1: Category | D1: Item | E1: Price Per Unit | F1: Quantity | G1: Total Spent | H1: Payment Method | I1: Location | J1: Transaction Date | K1: Discount Applied
A2: TXN_1113295 | B2: CUST_11 | C2: Milk Products | D2: Item_25_MILK | E2: 41 | F2: 10 | G2: 410 | H2: Digital Wallet | I2: Online | J2: 44796 | K2: FALSE
A3: TXN_1172555 | B3: CUST_08 | C3: Beverages | D3: Item_25_BEV | E3: 41 | F3: 10 | G3: 410 | H3: Cash | I3: In-store | J3: 45017 | K3: TRUE
A4: TXN_1273334 | B4: CUST_22 | C4: Beverages | D4: Item_25_BEV | E4: 41 | F4: 10 | G4: 410 | H4: Digital Wallet | I4: In-store | J4: 44869 | K4: TRUE
A5: TXN_1599706 | B5: CUST_14 | C5: Furniture | D5: Item_25_FUR | E5: 41 | F5: 10 | G5: 410 | H5: Credit Card | I5: In-store | J5: 45375 | K5: TRUE
A6: TXN_1654267 | B6: CUST_03 | C6: Milk Products | D6: Item_25_MILK | E6: 41 | F6: 10 | G6: 410 | H6: Cash | I6: Online | J6: 45374 | K6: FALSE
A7: TXN_1860120 | B7: CUST_01 | C7: Furniture | D7: Item_25_FUR | E7: 41 | F7: 10 | G7: 410 | H7: Digital Wallet | I7: Online | J7: 44580 | K7: TRUE
A8: TXN_1938135 | B8: CUST_17 | C8: Butchers | D8: Item_25_BUT | E8: 41 | F8: 10 | G8: 410 | H8: Digital Wallet | I8: In-store | J8: 45280 | K8: TRUE
A9: TXN_2208547 | B9: CUST_05 | C9: Beverages | D9: Item_25_BEV | E9: 41 | F9: 10 | G9: 410 | H9: Credit Card | I9: Online | J9: 44615 | K9: TRUE
A10: TXN_2386101 | B10: CUST_14 | C10: Furniture | D10: Item_25_FUR | E10: 41 | F10: 10 | G10: 410 | H10: Digital Wallet | I10: In-store | J10: 45661 | K10: TRUE
A11: TXN_2624160 | B11: CUST_16 | C11: Butchers | D11: Item_25_BUT | E11: 41 | F11: 10 | G11: 410 | H11: Digital Wallet | I11: Online | J11: 44731 | K11: TRUE
A12: TXN_2971834 | B12: CUST_11 | C12: Butchers | D12: Item_25_BUT | E12: 41 | F12: 10 | G12: 410 | H12: Credit Card | I12: Online | J12: 44802 | K12: TRUE
A13: TXN_3342443 | B13: CUST_08 | C13: Butchers | D13: Item_25_BUT | E13: 41 | F13: 10 | G13: 410 | H13: Credit Card | I13: In-store | J13: 45202 | K13: TRUE
... A7580: TXN_9911488 | B7580: CUST_25 | C7580: Electric household essentials | D7580: Item_1_EHE | E7580: 5 | F7580: 1 | G7580: 5 | H7580: Digital Wallet | I7580: Online | J7580: 45537 | K7580: FALSE
H8349: =TRIM(H:H) -> 0

Sheet formulas
B3: ADD | C3: ='retail_store_sales (1)'!E11 +'retail_store_sales (1)'!G11 -> 451 | F3: {=TRANSPOSE(B3:C32)} -> ADD | G3: SUBTRACT | H3: MULTIPLICATION | I3: DIVISION | J3: SUM | K3: MEAN(AVERAGE) | L3: MEDIAN | M3: COUNT | N3: COUNTA | O3: MIN | P3: MAX | Q3: IF | R3: CONCAT | S3: LEN | T3: TRIM | U3: UPPER | V3: LOWER | W3: PROPER | X3: SUMIF | Y3: COUNTIF | Z3: AVERAGEIF | AA3: SUMIFS | AB3: LEFT | AC3: RIGHT | AD3: MID | AE3: ROUND | AF3: TODAY/NOW | AG3: DATE TO TEXT | AH3: UNIQUE | AI3: TRANSPOSE
B4: SUBTRACT | C4: ='retail_store_sales (1)'!G16 -'retail_store_sales (1)'!E16 -> 369 | F4: 451 | G4: 369 | H4: 410 | I4: 41 | J4: 988513 | K4: 23.428882 | L4: 23 | M4: 7579 | N4: 7579 | O4: 5 | P4: 410 | Q4: DISCOUNT NOT ALLOWED | R4: Digital Wallet Online | S4: 14 | T4: Digital Wallet | U4: 0 | V4: 0 | W4: 0 | X4: 183562.5 | Y4: 2583 | Z4: 33.208406 | AA4: 410 | AB4: Dig | AC4: 0 | AD4: edit | AE4: 0 | AF4: 46204 | AG4: 0 | AH4: Category | AI4: Milk Products
B5: MULTIPLICATION | C5: ='retail_store_sales (1)'!E19 *'retail_store_sales (1)'!F19 -> 410
B6: DIVISION | C6: ='retail_store_sales (1)'!G20 /'retail_store_sales (1)'!F19 -> 41
B7: SUM | C7: =SUM('retail_store_sales (1)'!G:G) -> 988513
B8: MEAN(AVERAGE) | C8: =AVERAGE('retail_store_sales (1)'!E:E) -> 23.428882
B9: MEDIAN | C9: =MEDIAN('retail_store_sales (1)'!E:E) -> 23
B10: COUNT | C10: =COUNT('retail_store_sales (1)'!G:G) -> 7579
B11: COUNTA | C11: =COUNTA(Table1[Payment Method]) -> 7579
B12: MIN | C12: =MIN('retail_store_sales (1)'!G:G) -> 5
B13: MAX | C13: =MAX('retail_store_sales (1)'!G:G) -> 410
B14: IF | C14: =IF('retail_store_sales (1)'!K2 = "TRUE", "DISCOUNT ALLOWED", "DISCOUNT NOT ALLOWED") -> DISCOUNT NOT ALLOWED
B15: CONCAT | C15: =_xlfn.CONCAT('retail_store_sales (1)'!H2, " ",'retail_store_sales (1)'!I2) -> Digital Wallet Online
B16: LEN | C16: =LEN('retail_store_sales (1)'!H2) -> 14
B17: TRIM | C17: =TRIM('retail_store_sales (1)'!H4) -> Digital Wallet
B18: UPPER
B19: LOWER
B20: PROPER
B21: SUMIF | C21: =SUMIF('retail_store_sales (1)'!G:G, ">300") -> 183562.5
B22: COUNTIF | C22: =COUNTIF(Table1[Payment Method], "=Cash") -> 2583
B23: AVERAGEIF | C23: =AVERAGEIF('retail_store_sales (1)'!G:G, ">200",'retail_store_sales (1)'!E:E) -> 33.208406
B24: SUMIFS | C24: =SUMIFS('retail_store_sales (1)'!E:E,'retail_store_sales (1)'!H:H,"Cash",'retail_store_sales (1)'!G:G, ">400") -> 410
B25: LEFT | C25: =LEFT('retail_store_sales (1)'!H7, 3) -> Dig
B26: RIGHT
B27: MID | C27: =MID('retail_store_sales (1)'!H9,3,4) -> edit
B28: ROUND | C28: =ROUND(E22,2) -> 0
B29: TODAY/NOW | C29: =TODAY() -> 46204
B30: DATE TO TEXT
B31: UNIQUE | C31: {=_xlfn.UNIQUE('retail_store_sales (1)'!C:C)} -> Category
B32: TRANSPOSE | C32: Milk Products
C33: Beverages
C34: Furniture
C35: Butchers
C36: Food
C37: Electric household essentials
C38: Computers and electric accessories
C39: Patisserie
C40: 0

Sheet pivot table
A2: Row Labels | B2: Sum of Total Spent
A3: Beverages | B3: 124513
A4: Butchers | B4: 136146.5
A5: Computers and electric accessories | B5: 126621.5
A6: Electric household essentials | B6: 124381.5
A7: Food | B7: 122434.5
A8: Furniture | B8: 120756.5
A9: Milk Products | B9: 116538.5
A10: Patisserie | B10: 117121
A11: Grand Total | B11: 988513
